bukalapak_scrapper/__init__.py
bukalapak_scrapper/scrapper.py
bukalapak_scraper-0.1.0.dist-info/LICENSE
bukalapak_scraper-0.1.0.dist-info/METADATA
bukalapak_scraper-0.1.0.dist-info/WHEEL
bukalapak_scraper-0.1.0.dist-info/top_level.txt
bukalapak_scraper-0.1.0.dist-info/RECORD
